typst2anki/__init__.py
typst2anki/api.py
typst2anki/generator.py
typst2anki/get_data.py
typst2anki/main.py
typst2anki/parse.py
typst2anki/process.py
typst2anki-0.1.1.dist-info/LICENSE
typst2anki-0.1.1.dist-info/METADATA
typst2anki-0.1.1.dist-info/WHEEL
typst2anki-0.1.1.dist-info/entry_points.txt
typst2anki-0.1.1.dist-info/top_level.txt
typst2anki-0.1.1.dist-info/RECORD
