Metadata-Version: 2.1
Name: typst2anki
Version: 0.1.1
Summary: Convert Typst files into Anki cards automatically.
Home-page: https://github.com/sgomezsal/typst2anki
Author: sgomezsal
Author-email: sgomezsalazar7@gmail.com
Classifier: Programming Language :: Python :: 3
Classifier: License :: OSI Approved :: MIT License
Classifier: Operating System :: OS Independent
Requires-Python: >=3.8
License-File: LICENSE
Requires-Dist: requests
